cutout_fits/__init__.py
cutout_fits/_version.py
cutout_fits/_version.pyi
cutout_fits/casda.py
cutout_fits/casda_login.py
cutout_fits/cutout.py
cutout_fits/logger.py
cutout_fits/py.typed
cutout_fits-0.1.2.dist-info/METADATA
cutout_fits-0.1.2.dist-info/WHEEL
cutout_fits-0.1.2.dist-info/entry_points.txt
cutout_fits-0.1.2.dist-info/licenses/LICENSE
cutout_fits-0.1.2.dist-info/RECORD
